pyvips/__init__.py
pyvips/base.py
pyvips/decls.py
pyvips/enums.py
pyvips/error.py
pyvips/gobject.py
pyvips/gvalue.py
pyvips/pyvips_build.py
pyvips/version.py
pyvips/vimage.py
pyvips/vinterpolate.py
pyvips/vobject.py
pyvips/voperation.py
pyvips-2.1.0.dist-info/DESCRIPTION.rst
pyvips-2.1.0.dist-info/METADATA
pyvips-2.1.0.dist-info/RECORD
pyvips-2.1.0.dist-info/WHEEL
pyvips-2.1.0.dist-info/metadata.json
pyvips-2.1.0.dist-info/top_level.txt
