Metadata-Version: 2.0
Name: pyvips
Version: 2.1.0
Summary: binding for the libvips image processing library, ABI mode
Home-page: https://github.com/jcupitt/pyvips
Author: John Cupitt
Author-email: jcupitt@gmail.com
License: MIT
Keywords: image processing
Platform: UNKNOWN
Classifier: Development Status :: 5 - Production/Stable
Classifier: Environment :: Console
Classifier: Intended Audience :: Developers
Classifier: Intended Audience :: Science/Research
Classifier: Topic :: Multimedia :: Graphics
Classifier: Topic :: Multimedia :: Graphics :: Graphics Conversion
Classifier: License :: OSI Approved :: MIT License
Classifier: Programming Language :: Python :: 2.7
Classifier: Programming Language :: Python :: 3
Classifier: Programming Language :: Python :: 3.3
Classifier: Programming Language :: Python :: 3.4
Classifier: Programming Language :: Python :: 3.5
Classifier: Programming Language :: Python :: 3.6
Classifier: Programming Language :: Python :: Implementation :: PyPy
Classifier: Programming Language :: Python :: Implementation :: CPython
Requires-Dist: cffi (>=1.0.0)
Provides-Extra: doc
Requires-Dist: sphinx; extra == 'doc'
Requires-Dist: sphinx-rtd-theme; extra == 'doc'
Provides-Extra: test
Requires-Dist: cffi (>=1.0.0); extra == 'test'
Requires-Dist: pytest; extra == 'test'
Requires-Dist: pytest-catchlog; extra == 'test'
Requires-Dist: pytest-flake8; extra == 'test'
